LICENSE
README.md
setup.py
melo/__init__.py
melo/api.py
melo/app.py
melo/attentions.py
melo/commons.py
melo/download_utils.py
melo/init_downloads.py
melo/main.py
melo/mel_processing.py
melo/models.py
melo/modules.py
melo/split_utils.py
melo/transforms.py
melo/utils.py
melo/text/__init__.py
melo/text/chinese.py
melo/text/chinese_bert.py
melo/text/chinese_mix.py
melo/text/cleaner.py
melo/text/cleaner_multiling.py
melo/text/cmudict_cache.pickle
melo/text/english.py
melo/text/english_bert.py
melo/text/french.py
melo/text/french_bert.py
melo/text/japanese.py
melo/text/japanese_bert.py
melo/text/ko_dictionary.py
melo/text/korean.py
melo/text/opencpop-strict.txt
melo/text/spanish.py
melo/text/spanish_bert.py
melo/text/symbols.py
melo/text/tone_sandhi.py
melo/text/english_utils/__init__.py
melo/text/english_utils/abbreviations.py
melo/text/english_utils/number_norm.py
melo/text/english_utils/time_norm.py
melo/text/es_phonemizer/__init__.py
melo/text/es_phonemizer/base.py
melo/text/es_phonemizer/cleaner.py
melo/text/es_phonemizer/es_symbols.txt
melo/text/es_phonemizer/es_to_ipa.py
melo/text/es_phonemizer/example_ipa.txt
melo/text/es_phonemizer/gruut_wrapper.py
melo/text/es_phonemizer/punctuation.py
melo/text/es_phonemizer/spanish_symbols.txt
melo/text/fr_phonemizer/__init__.py
melo/text/fr_phonemizer/base.py
melo/text/fr_phonemizer/cleaner.py
melo/text/fr_phonemizer/example_ipa.txt
melo/text/fr_phonemizer/fr_to_ipa.py
melo/text/fr_phonemizer/french_abbreviations.py
melo/text/fr_phonemizer/french_symbols.txt
melo/text/fr_phonemizer/gruut_wrapper.py
melo/text/fr_phonemizer/punctuation.py
melotts.egg-info/PKG-INFO
melotts.egg-info/SOURCES.txt
melotts.egg-info/dependency_links.txt
melotts.egg-info/entry_points.txt
melotts.egg-info/requires.txt
melotts.egg-info/top_level.txt
test/test_base_model_tts_package.py